[
{
"name": "Provocatuer",
"allyCode": "824828412",
"discordId": "",
"userIcon": ":green_circle:"
} ,
{
"name": "Rollzy",
"allyCode": "465387769",
"discordId": "123217272163663872",
"userIcon": ":green_circle:"
} ,
{
"name": "",
"allyCode": "891563558",
"discordId": "",
"userIcon": ":green_circle:"
} ,
{
"name": "",
"allyCode": "172716618",
"discordId": "",
"userIcon": ":green_circle:"
} ,
{
"name": "",
"allyCode": "791283892",
"discordId": "",
"userIcon": ":green_circle:"
} ,
{
"name": "",
"allyCode": "229471315",
"discordId": "",
"userIcon": ":green_circle:"
} ,
{
"name": "",
"allyCode": "715679315",
"discordId": "",
"userIcon": ":green_circle:"
} ,
{
"name": "",
"allyCode": "175848723",
"discordId": "",
"userIcon": ":green_circle:"
} ,
{
"name": "",
"allyCode": "412993847",
"discordId": "",
"userIcon": ":green_circle:"
} ,
{
"name": "",
"allyCode": "617972559",
"discordId": "",
"userIcon": ":green_circle:"
} ,
{
"name": "",
"allyCode": "781645615",
"discordId": "304674535485997057",
"userIcon": ":green_circle:"
} ,
{
"name": "",
"allyCode": "712137614",
"discordId": "",
"userIcon": ":green_circle:"
} ,
{
"name": "",
"allyCode": "534695487",
"discordId": "",
"userIcon": ":green_circle:"
} ,
{
"name": "",
"allyCode": "874394443",
"discordId": "",
"userIcon": ":red_circle:"
} ,
{
"name": "",
"allyCode": "558653669",
"discordId": "",
"userIcon": ":green_circle:"
} ,
{
"name": "",
"allyCode": "632268236",
"discordId": "300270094871822336",
"userIcon": ":green_circle:"
} ,
{
"name": "",
"allyCode": "598247923",
"discordId": "",
"userIcon": ":green_circle:"
} ,
{
"name": "",
"allyCode": "551778652",
"discordId": "",
"userIcon": ":green_circle:"
} ,
{
"name": "",
"allyCode": "123429484",
"discordId": "",
"userIcon": ":green_circle:"
} ,
{
"name": "",
"allyCode": "994867427",
"discordId": "",
"userIcon": ":green_circle:"
} ,
{
"name": "",
"allyCode": "957973879",
"discordId": "",
"userIcon": ":green_circle:"
} ,
{
"name": "",
"allyCode": "929675914",
"discordId": "",
"userIcon": ":green_circle:"
} ,
{
"name": "",
"allyCode": "917163673",
"discordId": "",
"userIcon": ":green_circle:"
} ,
{
"name": "",
"allyCode": "513939693",
"discordId": "",
"userIcon": ":green_circle:"
} ,
{
"name": "",
"allyCode": "752981686",
"discordId": "",
"userIcon": ":green_circle:"
} ,
{
"name": "",
"allyCode": "856883111",
"discordId": "",
"userIcon": ":green_circle:"
} ,
{
"name": "",
"allyCode": "232895159",
"discordId": "406056489673949184",
"userIcon": ":green_circle:"
} ,
{
"name": "",
"allyCode": "612977345",
"discordId": "",
"userIcon": ":green_circle:"
} ,
{
"name": "",
"allyCode": "396882831",
"discordId": "",
"userIcon": ":green_circle:"
} ,
{
"name": "",
"allyCode": "512848577",
"discordId": "",
"userIcon": ":green_circle:"
} ,
{
"name": "",
"allyCode": "258616484",
"discordId": "",
"userIcon": ""
} ,
{
"name": "",
"allyCode": "396937529",
"discordId": "349286348378734595",
"userIcon": ":green_circle:"
} ,
{
"name": "",
"allyCode": "513981686",
"discordId": "",
"userIcon": ":green_circle:"
} ,
{
"name": "",
"allyCode": "733537886",
"discordId": "",
"userIcon": ":green_circle:"
} ,
{
"name": "",
"allyCode": "367157516",
"discordId": "",
"userIcon": ""
} ,
{
"name": "",
"allyCode": "876852762",
"discordId": "",
"userIcon": ":green_circle:"
} ,
{
"name": "",
"allyCode": "615684747",
"discordId": "",
"userIcon": ":red_circle:"
} ,
{
"name": "",
"allyCode": "913112565",
"discordId": "",
"userIcon": ":green_circle:"
} ,
{
"name": "",
"allyCode": "447273616",
"discordId": "",
"userIcon": ":red_circle:"
} ,
{
"name": "",
"allyCode": "318458483",
"discordId": "",
"userIcon": ":red_circle:"
} ,
{
"name": "",
"allyCode": "224635177",
"discordId": "",
"userIcon": ":red_circle:"
} ,
{
"name": "",
"allyCode": "913112565",
"discordId": "",
"userIcon": ":red_circle:"
} ,
{
"name": "smitheng",
"allyCode": "764884462",
"discordId": "",
"userIcon": ":green_circle:"
} ,
{
"name": "",
"allyCode": "148989987",
"discordId": "",
"userIcon": ""
} ,
{
"name": "",
"allyCode": "851732563",
"discordId": "",
"userIcon": ""
} ,
{
"name": "",
"allyCode": "889757984",
"discordId": "",
"userIcon": ""
} ,
{
"name": "",
"allyCode": "117529944",
"discordId": "",
"userIcon": ":red_circle:"
} ,
{
"name": "",
"allyCode": "498825446",
"discordId": "",
"userIcon": ":red_circle:"
} ,
{
"name": "",
"allyCode": "538131162",
"discordId": "",
"userIcon": ":red_circle:"
} ,
{
"name": "",
"allyCode": "466352168",
"discordId": "",
"userIcon": ":red_circle:"
} ,
{
"name": "",
"allyCode": "385929234",
"discordId": "",
"userIcon": ":red_circle:"
} ,
{
"name": "",
"allyCode": "258616484",
"discordId": "",
"userIcon": ":red_circle:"
} ,
{
"name": "",
"allyCode": "328642693",
"discordId": "",
"userIcon": ":red_circle:"
} ,
]
